ef2gql/__init__.py
ef2gql/cmd.py
ef2gql-0.9.dist-info/DESCRIPTION.rst
ef2gql-0.9.dist-info/METADATA
ef2gql-0.9.dist-info/RECORD
ef2gql-0.9.dist-info/WHEEL
ef2gql-0.9.dist-info/entry_points.txt
ef2gql-0.9.dist-info/metadata.json
ef2gql-0.9.dist-info/top_level.txt
